magic_timer/__init__.py
magic_timer/format_seconds.py
magic_timer/magic_timer.py
magic_timer-1.0.0.dist-info/LICENSE
magic_timer-1.0.0.dist-info/METADATA
magic_timer-1.0.0.dist-info/WHEEL
magic_timer-1.0.0.dist-info/top_level.txt
magic_timer-1.0.0.dist-info/RECORD
