Metadata-Version: 2.1
Name: magic-timer
Version: 1.0.0
Summary: Conveniently get a rough idea of how long things take.
Home-page: https://github.com/sradc/magic-timer
Author: Sidney Radcliffe
Author-email: sidneyradcliffe@gmail.com
License: UNKNOWN
Platform: UNKNOWN
Classifier: Programming Language :: Python :: 3
Classifier: License :: OSI Approved :: MIT License
Classifier: Operating System :: OS Independent
Requires-Python: >=3.6
License-File: LICENSE
